star_metrics_sqlite
